{
  "Host": [
    "amy poehler",
    "tina fey"
  ],
  "award_data": {},
  "Best Motion Picture - Drama": {
    "Presenters": [
      "robert pattinson",
      "amanda seyfried"
    ],
    "Nominees": [
      "argo",
      "django unchained",
      "lincoln",
      "zero dark thirty",
      "life of pi"
    ],
    "Winner": "argo"
  },
  "Best Motion Picture - Musical or Comedy": {
    "Presenters": [
      "will ferrell",
      "kristen wiig"
    ],
    "Nominees": [
      "les miserables",
      "silver linings playbook",
      "moonrise kingdom",
      "salmon fishing in the yemen",
      "the best exotic marigold hotel"
    ],
    "Winner": "les miserables"
  }
}